setup.py
SimpleCoinbaseBot.egg-info/PKG-INFO
SimpleCoinbaseBot.egg-info/SOURCES.txt
SimpleCoinbaseBot.egg-info/dependency_links.txt
SimpleCoinbaseBot.egg-info/entry_points.txt
SimpleCoinbaseBot.egg-info/requires.txt
SimpleCoinbaseBot.egg-info/top_level.txt
simplecoinbasebot/__init__.py
simplecoinbasebot/color.py
simplecoinbasebot/getch.py
simplecoinbasebot/run.py
simplecoinbasebot/simplebot.py
simplecoinbasebot/termsize.py
simplecoinbasebot/top.py