Metadata-Version: 1.1
Name: SimpleCoinbaseBot
Version: 1.4.0
Summary: UNKNOWN
Home-page: https://github.com/mtingers/simple-coinbase-bot
Author: Matth Ingersoll
Author-email: matth@mtingers.com
License: BSD 2-Clause License
Platform: UNKNOWN
Classifier: Intended Audience :: Developers
Classifier: License :: OSI Approved :: BSD License
Classifier: Programming Language :: Python :: 3
Classifier: Programming Language :: Python :: 3.4
Classifier: Programming Language :: Python :: 3.5
Classifier: Programming Language :: Python :: 3.6
Classifier: Programming Language :: Python :: 3.7
Classifier: Programming Language :: Python :: 3.8
Classifier: Programming Language :: Python :: 3.9
